{"follow_request_sent": false, "profile_use_background_image": false, "geo_enabled": false, "verified": false, "profile_image_url_https": "https://si0.twimg.com/profile_images/579561161/jaime_normal.jpg", "profile_sidebar_fill_color": "99CC33", "is_translator": false, "id": 43525471, "profile_text_color": "3E4415", "followers_count": 168, "profile_sidebar_border_color": "829D5E", "id_str": "43525471", "default_profile_image": false, "listed_count": 1, "utc_offset": -18000, "statuses_count": 354, "description": "enjoy music, nature, the beach, and good eats", "friends_count": 339, "location": "Raleigh, North Carolina", "profile_link_color": "D02B55", "profile_image_url": "http://a1.twimg.com/profile_images/579561161/jaime_normal.jpg", "notifications": false, "show_all_inline_media": false, "profile_background_image_url_https": "https://si0.twimg.com/profile_background_images/16678878/puerto_rico3.jpg", "profile_background_color": "352726", "profile_background_image_url": "http://a1.twimg.com/profile_background_images/16678878/puerto_rico3.jpg", "screen_name": "jzabala", "lang": "en", "profile_background_tile": false, "favourites_count": 20, "name": "Jaime Zabala", "url": null, "created_at": "Sat May 30 13:10:51 +0000 2009", "contributors_enabled": false, "time_zone": "Eastern Time (US & Canada)", "protected": true, "default_profile": false, "following": false}